[{
	"name": "double",
	"weights": {
		"military": 2,
		"points": 2,
		"coins": 2,
		"cards": 2,
		"wonder": 2,
		"cost": 2,
		"build": 2
	}
},{
	"name": "unit",
	"weights": {
		"military": 1,
		"points": 1,
		"coins": 1,
		"cards": 1,
		"wonder": 1,
		"cost": 1,
		"build": 1
	}
}, {
	"name": "3p_p_t56",
	"weights": {
		"military": 2,
		"points": 2,
		"coins": 2.6,
		"cards": 2.8,
		"wonder": 2.9,
		"cost": 1.1,
		"build": 2.2
	}
}, {
	"name": "3p_p_r55",
	"weights": {
		"military": 2.2,
		"points": 3.5,
		"coins": 0.5,
		"cards": 3.4,
		"wonder": 3.3,
		"cost": 1.6,
		"build": 0.8
	}
}, {
	"name": "3p_p_e54",
	"weights": {
		"military": 0.7,
		"points": 3,
		"coins": 3.7,
		"cards": 2.5,
		"wonder": 3.9,
		"cost": 4.6,
		"build": 2.7
	}
}, {
	"name": "3p_p_e54b",
	"weights": {
		"military": 2.9,
		"points": 1,
		"coins": 2.4,
		"cards": 1.2,
		"wonder": 4.7,
		"cost": 2.1,
		"build": 2.2
	}
}, {
	"name": "3p_p_e54c",
	"weights": {
		"military": 3,
		"points": 2.3,
		"coins": 3.7,
		"cards": 3,
		"wonder": 3.7,
		"cost": 5.1,
		"build": 2.1
	}
}, {
	"name": "3p_p_e54d",
	"weights": {
		"military": 1.3,
		"points": 3.3,
		"coins": 4.3,
		"cards": 3.4,
		"wonder": 3.9,
		"cost": 4.6,
		"build": 2.7
	}
}, {
	"name": "3p_w_e49",
	"weights": {
		"military": 3.1,
		"points": 0.8,
		"coins": 2.3,
		"cards": 1.9,
		"wonder": 3.7,
		"cost": 1.4,
		"build": 3.5
	}
}, {
	"name": "3p_w_r49",
	"weights": {
		"military": 2.7,
		"points": 1,
		"coins": 1,
		"cards": 0.9,
		"wonder": 2.9,
		"cost": 1.6,
		"build": 1.1
	}
}, {
	"name": "3p_w_999",
	"weights": {
		"military": 3,
		"points": 0.8,
		"coins": 2.3,
		"cards": 1.3,
		"wonder": 3.7,
		"cost": 1.4,
		"build": 4
	}
}, {
    "name":"4p_p_e51",
    "weights":{
        "military":3.1,
        "points":2.3,
        "coins":3.8,
        "cards":3,
        "wonder":3,
        "cost":4.5,
        "build":2.1
    }
}, {
    "name":"4p_p_e51b",
    "weights":{
        "military":3.1,
        "points":2.3,
        "coins":3,
        "cards":3,
        "wonder":3,
        "cost":4.6,
        "build":2.1
    }
}, {
    "name":"4p_p_e51c",
    "weights":{
        "military":3,
        "points":2.3,
        "coins":3.8,
        "cards":3,
        "wonder":3.7,
        "cost":4.5,
        "build":2.1
    }
}, {
    "name":"4p_p_r49",
    "weights":{
        "military":1.7,
        "points":1.8,
        "coins":3.1,
        "cards":1.1,
        "wonder":4,
        "cost":1.5,
        "build":1.5
    }
}, {
    "name":"4p_p_r49b",
    "weights":{
        "military":1.7,
        "points":1.3,
        "coins":3.1,
        "cards":2.1,
        "wonder":4,
        "cost":1.5,
        "build":1.5
    }
}, {
    "name":"5p_p_r51",
    "weights":{
        "military":1.1,
        "points":1,
        "coins":1.3,
        "cards":1,
        "wonder":1,
        "cost":1,
        "build":1
    }
}, {
    "name":"6p_p_e52",
    "weights":{
        "military":1.1,
        "points":2,
        "coins":4,
        "cards":1.4,
        "wonder":2.7,
        "cost":2,
        "build":2.5
    }
}, {
    "name":"6p_p_u52",
    "weights":{
        "military":1,
        "points":1,
        "coins":1.7,
        "cards":1,
        "wonder":1.4,
        "cost":1,
        "build":1
    }
}, {
    "name":"6p_p_r51",
    "weights":{
        "military":1.2,
        "points":2.9,
        "coins":0.9,
        "cards":3.3,
        "wonder":2.5,
        "cost":2.6,
        "build":1.9
    }
}, {
    "name": "4p_p_m51",
    "weights": {
		"military": 3.4,
		"points": 2.5,
		"coins": 2.8,
		"cards": 3.3,
		"wonder": 3.9,
		"cost": 3.3,
		"build": 1.7
	}
}, {
    "name": "4p_p_2a",
	"weights": {
		"military": 1.3,
		"points": 1,
		"coins": 1.7,
		"cards": 1,
		"wonder": 3.9,
		"cost": 1,
		"build": 2.7
	}
}, {
	"name": "4p_p_2b",
	"weights": {
		"military": 1.3,
		"points": 3.3,
		"coins": 4,
		"cards": 3.4,
		"wonder": 3.9,
		"cost": 4.6,
		"build": 2.7
	}
}
]